listen/__init__.py
listen/__main__.py
listen/main.py
listen/mic.py
listen/STT/__init__.py
listen/STT/as_client.py
listen/STT/as_service.py
listen/STT/audio.py
listen/STT/engine.py
listen/STT/exception.py
listen/STT/utils.py
stt_listen-2.4.2.dist-info/LICENSE
stt_listen-2.4.2.dist-info/METADATA
stt_listen-2.4.2.dist-info/WHEEL
stt_listen-2.4.2.dist-info/entry_points.txt
stt_listen-2.4.2.dist-info/top_level.txt
stt_listen-2.4.2.dist-info/RECORD
