Metadata-Version: 2.1
Name: stt-listen
Version: 2.4.2
Summary: Transcribe long audio files with STT or use the streaming interface
Home-page: https://gitlab.com/waser-technologies/technologies/listen
Author: Danny Waser
License: LICENSE
Requires-Python: >=3.8,<3.11
License-File: LICENSE
Requires-Dist: coqui-stt-model-manager (>=0.0.21)
Requires-Dist: numpy (>=1.15.1)
Requires-Dist: pyaudio (~=0.2.12)
Requires-Dist: webrtcvad (~=2.0.10)
Requires-Dist: scipy (>=1.1.0)
Requires-Dist: prompt-toolkit (<3.1.0,>=2.0.0)
Requires-Dist: toml (~=0.10.2)
Requires-Dist: sanic (~=22.6.0)
Requires-Dist: ffmpeg-python (~=0.2.0)
Requires-Dist: websockets (~=10.3)
Requires-Dist: deepmultilingualpunctuation
